[{"id":1,"target_date":"2026-01-23","main_work_id":122,"main_headline":"これは買い。評価5.0が99%OFF","main_reason":"ゲーム式訓練で厳しいオナニーが好きなM男必見。5.0評価でたったの¥12はマジで破格。耐久テストをクリアするまで帰れない！今すぐ買っとけ。","main_category":"asmr","sub1_work_id":104,"sub1_one_liner":"ゲームならこれ。密着パイズリ最高","sub1_category":"game","sub2_work_id":128,"sub2_one_liner":"安眠系の2番手も良いやつ","sub2_category":"asmr","cheapest_work_ids":[128,105,122,120,114,110,108,102,98,121],"high_discount_work_ids":[128,122,121,120,119,114,110,109,108,105],"high_rating_work_ids":[205,192,3,8,152,134,130,128,122,116],"total_sale_count":164,"dlsite_count":104,"fanza_count":60,"max_discount_rate":99,"ogp_image_url":"https://pub-93efa5c1650c4aed8308423fc2a46538.r2.dev/ogp/sale-2026-01-23.png","created_at":"2026-01-22 17:21:53","updated_at":"2026-01-22 17:21:53"}]